backports.csv-1.0.6-py3.6-nspkg.pth
backports/csv.py
backports.csv-1.0.6.dist-info/METADATA
backports.csv-1.0.6.dist-info/RECORD
backports.csv-1.0.6.dist-info/WHEEL
backports.csv-1.0.6.dist-info/namespace_packages.txt
backports.csv-1.0.6.dist-info/top_level.txt
