Metadata-Version: 1.1
Name: backports.csv
Version: 1.0.6
Summary: Backport of Python 3 csv module
Home-page: https://github.com/ryanhiebert/backports.csv
Author: Ryan Hiebert
Author-email: ryan@ryanhiebert.com
License: UNKNOWN
Platform: UNKNOWN
Classifier: Programming Language :: Python
Classifier: Programming Language :: Python :: 2
Classifier: Programming Language :: Python :: 2.6
Classifier: Programming Language :: Python :: 2.7
Classifier: Programming Language :: Python :: 3
Classifier: Programming Language :: Python :: 3.3
Classifier: Programming Language :: Python :: 3.4
Classifier: Programming Language :: Python :: 3.5
Classifier: Programming Language :: Python :: 3.6
